.gitignore
LICENSE
MANIFEST.in
README.md
README.rst
requirements.txt
setup.py
projecture/__init__.py
projecture/cmdline.py
projecture/projecture.py
projecture.egg-info/PKG-INFO
projecture.egg-info/SOURCES.txt
projecture.egg-info/dependency_links.txt
projecture.egg-info/entry_points.txt
projecture.egg-info/not-zip-safe
projecture.egg-info/top_level.txt
projecture/projects/python/myproject/LICENSE
projecture/projects/python/myproject/MANIFEST.in
projecture/projects/python/myproject/README.md
projecture/projects/python/myproject/README.rst
projecture/projects/python/myproject/requirements.txt
projecture/projects/python/myproject/setup.py
projecture/projects/python/myproject/myproject/__init__.py
projecture/projects/python/myproject/myproject/cmdline.py
projecture/projects/python/myproject/myproject/myproject.py
projecture/projects/python/myproject/myproject/tests/__init__.py
projecture/projects/python/myproject/myproject/tests/test_myproject.py
projecture/tests/__init__.py
projecture/tests/test_projecture.py