Metadata-Version: 1.1
Name: projecture
Version: 0.1.3
Summary: scaffolding/bootstrap generation tool
Home-page: http://github.com/diszgaurav/projecture
Author: Gaurav Verma
Author-email: diszgaurav@gmail.com
License: MIT
Keywords: project scaffolding
Platform: UNKNOWN
Classifier: Development Status :: 3 - Alpha
Classifier: License :: OSI Approved :: MIT License
Classifier: Programming Language :: Python :: 2.7
Classifier: Topic :: Software Development
Classifier: Operating System :: POSIX
